<?xml version="1.0" encoding="UTF-8"?>
<!DOCTYPE mapper
    PUBLIC "-//mybatis.org/DTD Mapper 3.0//EN"
    "http://mybatis.org/dtd/mybatis-3-mapper.dtd">
<mapper namespace="edu.sm.app.repository.UserRepository">

  <!-- 이메일로 사용자 조회 -->
  <select id="findByUserEmail" parameterType="string" resultType="User">
    SELECT
      patient_id          AS userId,
      email               AS userEmail,
      password            AS userPwd,
      name                AS userName,
      phone               AS userPhone,
      dob                 AS userDob,
      gender              AS userGender,
      address             AS userAddr,
      medical_history     AS userMedicalHistory,
      lifestyle_habits    AS userLifestyleHabits,
      account_status      AS userAccountStatus,
      language_preference AS languagePreference,
      provider,
      provider_id         AS providerId,
      user_role           AS userRole,
      created_at          AS userRegdate,
      updated_at          AS userUpdate
    FROM patient
    WHERE email = #{email}
  </select>

  <!-- OAuth 중복 체크 -->
  <select id="findByProviderAndProviderId" resultType="User">
    SELECT
      patient_id          AS userId,
      email               AS userEmail,
      password            AS userPwd,
      name                AS userName,
      phone               AS userPhone,
      dob                 AS userDob,
      gender              AS userGender,
      address             AS userAddr,
      medical_history     AS userMedicalHistory,
      lifestyle_habits    AS userLifestyleHabits,
      account_status      AS userAccountStatus,
      language_preference AS languagePreference,
      provider,
      provider_id         AS providerId,
      user_role           AS userRole,
      created_at          AS userRegdate,
      updated_at          AS userUpdate
    FROM patient
    WHERE provider = #{provider} AND provider_id = #{providerId}
  </select>

  <!-- 전체 사용자 조회 -->
  <select id="selectAll" resultType="User">
    SELECT
      patient_id          AS userId,
      email               AS userEmail,
      password            AS userPwd,
      name                AS userName,
      phone               AS userPhone,
      dob                 AS userDob,
      gender              AS userGender,
      address             AS userAddr,
      medical_history     AS userMedicalHistory,
      lifestyle_habits    AS userLifestyleHabits,
      account_status      AS userAccountStatus,
      language_preference AS languagePreference,
      provider,
      provider_id         AS providerId,
      user_role           AS userRole,
      created_at          AS userRegdate,
      updated_at          AS userUpdate
    FROM patient
  </select>

  <!-- ID로 사용자 조회 -->
  <select id="select" parameterType="int" resultType="User">
    SELECT
      patient_id          AS userId,
      email               AS userEmail,
      password            AS userPwd,
      name                AS userName,
      phone               AS userPhone,
      dob                 AS userDob,
      gender              AS userGender,
      address             AS userAddr,
      medical_history     AS userMedicalHistory,
      lifestyle_habits    AS userLifestyleHabits,
      account_status      AS userAccountStatus,
      language_preference AS languagePreference,
      provider,
      provider_id         AS providerId,
      user_role           AS userRole,
      created_at          AS userRegdate,
      updated_at          AS userUpdate
    FROM patient
    WHERE patient_id = #{userId}
  </select>

  <!-- 사용자 등록 -->
  <insert id="insert" parameterType="User" useGeneratedKeys="true" keyProperty="userId" keyColumn="patient_id">
    INSERT INTO patient (
      email, password, name, phone, dob,
      gender, address, medical_history, lifestyle_habits,
      account_status, language_preference,
      provider, provider_id, user_role, created_at
    ) VALUES (
               #{userEmail},
               #{userPwd},
               #{userName},
               #{userPhone},
               #{userDob},
               #{userGender},
               #{userAddr},
               #{userMedicalHistory},
               #{userLifestyleHabits},
               COALESCE(#{userAccountStatus}, 'active'),
               COALESCE(#{languagePreference}, 'ko'),
               #{provider},
               #{providerId},
               COALESCE(#{userRole}, 'ROLE_USER'),
               NOW()
             )
  </insert>

  <!-- 사용자 정보 수정 -->
  <update id="update" parameterType="User">
    UPDATE patient
    SET password   = #{userPwd},
        name       = #{userName},
        address    = #{userAddr},
        updated_at = NOW()
    WHERE patient_id = #{userId}
  </update>

  <!-- 사용자 삭제 (ID) -->
  <delete id="delete" parameterType="int">
    DELETE FROM patient WHERE patient_id = #{userId}
  </delete>

  <!-- 사용자 삭제 (Email) -->
  <delete id="deleteByEmail" parameterType="string">
    DELETE FROM patient WHERE email = #{email}
  </delete>

</mapper>
